{
	"format_version": "1.19.60",
	"minecraft:recipe_shaped": {
		"description": {
			"identifier": "haste:paper_of_suffering"
		},
		"tags": [
			"crafting_table"
		],
		"key": {
			"N": {
				"item": "minecraft:netherrack"
			},
			"P": {
				"item": "minecraft:paper"
			},
			"G": {
				"item": "minecraft:glowstone"
			},
			"C": {
				"item": "minecraft:crying_obsidian"
			}
		},
		"pattern": [
			" N ",
			"PGP",
			" C "
		],
		"result": {
			"count": 1,
			"item": "haste:paper_of_suffering"
		}
	}
}